{
  "name": "profile_images/4567890166/through the dome_5.webp",
  "bucket": "integridate.firebasestorage.app",
  "metageneration": 1,
  "generation": 1759595855881,
  "contentType": "image/webp",
  "storageClass": "STANDARD",
  "cacheControl": "public, max-age=31536000",
  "downloadTokens": [],
  "etag": "beivg19Ck5kOynvm9zKRd+kp3nY",
  "timeCreated": "2025-10-04T16:37:35.881Z",
  "updated": "2025-10-04T16:37:35.881Z",
  "size": 179734,
  "md5Hash": "z3SMf3sE01aoZ9ZJe85rYA==",
  "crc32c": "1092315781"
}