{
  "name": "profile_images/4567890220/through the dome_1.webp",
  "bucket": "integridate.firebasestorage.app",
  "metageneration": 1,
  "generation": 1763594576004,
  "contentType": "image/webp",
  "storageClass": "STANDARD",
  "cacheControl": "public, max-age=31536000",
  "downloadTokens": [],
  "etag": "Sv9TUrtmYtmtSisxi9j+AEl/6xU",
  "timeCreated": "2025-11-19T23:22:56.004Z",
  "updated": "2025-11-19T23:22:56.004Z",
  "size": 179734,
  "md5Hash": "z3SMf3sE01aoZ9ZJe85rYA==",
  "crc32c": "1092315781"
}