{
  "name": "profile_images/4567890103/through the dome_5.webp",
  "bucket": "integridate.firebasestorage.app",
  "metageneration": 1,
  "generation": 1763594568737,
  "contentType": "image/webp",
  "storageClass": "STANDARD",
  "cacheControl": "public, max-age=31536000",
  "downloadTokens": [],
  "etag": "zFTf7598xDVnA5ZMS/VJSoNcAX0",
  "timeCreated": "2025-11-19T23:22:48.737Z",
  "updated": "2025-11-19T23:22:48.737Z",
  "size": 179734,
  "md5Hash": "z3SMf3sE01aoZ9ZJe85rYA==",
  "crc32c": "1092315781"
}